midisim/MIDI.py
midisim/README.md
midisim/TMIDIX.py
midisim/__init__.py
midisim/helpers.py
midisim/midi_to_colab_audio.py
midisim/midisim.py
midisim/x_transformer_2_3_1.py
midisim/artwork/Project-Los-Angeles.png
midisim/artwork/README.md
midisim/artwork/Tegridy-Code-2025.png
midisim/artwork/__init__.py
midisim/artwork/midisim.png
midisim/embeddings/README.md
midisim/embeddings/__init__.py
midisim/models/README.md
midisim/models/__init__.py
midisim/models/midisim_small_pre_trained_model_2_epochs_43117_steps_0.3148_loss_0.9229_acc.pth
midisim-26.1.18.dist-info/licenses/LICENSE
midisim-26.1.18.dist-info/METADATA
midisim-26.1.18.dist-info/WHEEL
midisim-26.1.18.dist-info/top_level.txt
midisim-26.1.18.dist-info/RECORD
