Metadata-Version: 2.4
Name: midisim
Version: 26.1.18
Summary: Calculate, search, and analyze MIDI-to-MIDI similarity at scale
Author-email: Alex Lev <alexlev61@proton.me>
Maintainer-email: Alex Lev <alexlev61@proton.me>
License-Expression: Apache-2.0
Project-URL: Homepage, https://github.com/asigalov61/midisim
Project-URL: Documentation, https://github.com/asigalov61/midisim
Project-URL: Models, https://huggingface.co/projectlosangeles/midisim
Project-URL: Embeddings, https://huggingface.co/datasets/projectlosangeles/midisim-embeddings
Project-URL: Samples, https://huggingface.co/datasets/projectlosangeles/midisim-samples
Project-URL: Issues, https://github.com/asigalov61/midisim/issues
Project-URL: Discussions, https://github.com/asigalov61/midisim/discussions
Project-URL: Dataset, https://huggingface.co/datasets/projectlosangeles/Discover-MIDI-Dataset
Project-URL: SoundCloud, https://soundcloud.com/aleksandr-sigalov-61/
Keywords: MIDI,music,music AI,MIR,similarity,similarity search,symbolic music,MIDI similarity,music similarity,cosine somilarity,MIDI search,music search,music information retrieval,music analysis,MIDI analysis
Classifier: Development Status :: 5 - Production/Stable
Classifier: Intended Audience :: Developers
Classifier: Intended Audience :: Science/Research
Classifier: Intended Audience :: Education
Classifier: Operating System :: OS Independent
Classifier: Programming Language :: Python :: 3
Classifier: Programming Language :: Python :: 3 :: Only
Classifier: Programming Language :: Python :: 3.8
Classifier: Programming Language :: Python :: 3.9
Classifier: Programming Language :: Python :: 3.10
Classifier: Programming Language :: Python :: 3.11
Classifier: Programming Language :: Python :: 3.12
Classifier: Topic :: Multimedia :: Sound/Audio
Classifier: Topic :: Multimedia :: Sound/Audio :: MIDI
Classifier: Topic :: Scientific/Engineering :: Artificial Intelligence
Classifier: Topic :: Scientific/Engineering :: Information Analysis
Classifier: Topic :: Software Development :: Libraries :: Python Modules
Classifier: Environment :: Console
Classifier: Natural Language :: English
Classifier: Typing :: Typed
Requires-Python: >=3.8
License-File: LICENSE
Requires-Dist: tqdm
Requires-Dist: ipywidgets
Requires-Dist: hf-transfer
Requires-Dist: huggingface_hub
Requires-Dist: torch
Requires-Dist: einops
Requires-Dist: einx
Requires-Dist: torch-summary
Requires-Dist: matplotlib
Requires-Dist: numpy==1.26.4
Dynamic: license-file
